{"id":"4b0216b3-b6d9-46bd-817d-db4eae5f8599","timestamp":1732892711216,"matcher":{"static":{},"wildcard":{},"dynamic":{}},"prerendered":["/chart","/websites","/movie","/","/hospital","/health","/trail","/travel","/fitness","/health/h007","/trail/t003","/health/h002","/health/h009","/health/h001","/health/h006","/trail/t019","/trail/t009","/trail/t010","/trail/t013","/trail/t012","/trail/t002","/trail/t014","/trail/t001","/trail/t004","/trail/t016","/trail/t005","/trail/t015","/trail/t008","/trail/t007","/trail/t006","/health/h008","/health/h004","/trail/t011","/health/h005","/trail/t018","/health/h003","/trail/t017","/travel/v003","/travel/v006","/travel/v013","/travel/v005","/travel/v002","/travel/v015","/travel/v016","/travel/v011","/travel/v012","/travel/v010","/travel/v018","/travel/v014","/travel/v008","/travel/v017","/travel/v001","/travel/v009","/travel/v019","/travel/v007","/fitness/f012","/fitness/f009","/fitness/f013","/travel/v004","/fitness/f014","/fitness/f010","/fitness/f011","/fitness/f005","/fitness/f006","/fitness/f001","/travel/v020","/fitness/f018","/fitness/f003","/fitness/f002","/fitness/f016","/fitness/f008","/fitness/f017","/fitness/f015","/fitness/f004","/fitness/f019"]}