{"id":"629f01cf-c28e-4c9d-a61e-648db5f8def5","timestamp":1738894976273,"matcher":{"static":{},"wildcard":{},"dynamic":{}},"prerendered":["/movie","/","/websites","/hospital","/chart","/fitness","/health","/trail","/travel","/health/h007","/fitness/f018","/fitness/f004","/fitness/f003","/fitness/f005","/fitness/f009","/fitness/f016","/health/h009","/health/h008","/health/h001","/fitness/f013","/fitness/f017","/health/h003","/health/h005","/health/h006","/health/h002","/fitness/f002","/fitness/f010","/health/h004","/fitness/f019","/fitness/f008","/fitness/f015","/fitness/f006","/fitness/f012","/fitness/f014","/fitness/f001","/trail/t013","/fitness/f011","/trail/t014","/trail/t010","/trail/t012","/trail/t011","/trail/t019","/trail/t009","/trail/t003","/trail/t006","/trail/t008","/trail/t016","/trail/t004","/trail/t015","/trail/t007","/trail/t001","/trail/t005","/travel/v002","/trail/t018","/travel/v009","/travel/v001","/trail/t002","/trail/t017","/travel/v014","/travel/v010","/travel/v013","/travel/v003","/travel/v005","/travel/v015","/travel/v006","/travel/v008","/travel/v011","/travel/v012","/travel/v004","/travel/v018","/travel/v016","/travel/v007","/travel/v019","/travel/v022","/travel/v021","/travel/v017","/travel/v024","/travel/v025","/travel/v023","/travel/v020"]}