{"id":"c0c619a5-17bc-47e9-a1c4-909e842422d2","timestamp":1727949447797,"matcher":{"static":{},"wildcard":{},"dynamic":{}},"prerendered":["/websites","/","/movie","/hospital","/chart","/travel","/fitness","/trail","/health","/fitness/f018","/fitness/f016","/fitness/f006","/fitness/f012","/fitness/f004","/fitness/f010","/fitness/f013","/fitness/f017","/travel/v011","/travel/v003","/fitness/f001","/travel/v002","/fitness/f009","/travel/v013","/travel/v014","/fitness/f002","/travel/v001","/fitness/f003","/travel/v005","/travel/v012","/travel/v009","/fitness/f005","/travel/v006","/travel/v004","/fitness/f014","/travel/v008","/travel/v010","/fitness/f011","/fitness/f008","/fitness/f015","/trail/t013","/travel/v007","/trail/t011","/trail/t012","/trail/t019","/trail/t001","/trail/t003","/trail/t004","/trail/t005","/trail/t010","/trail/t007","/trail/t008","/trail/t015","/trail/t016","/trail/t006","/health/h002","/trail/t017","/trail/t018","/health/h001","/health/h008","/health/h007","/health/h004","/trail/t009","/health/h003","/health/h006","/trail/t002","/health/h005","/trail/t014","/health/h009"]}